butler/__init__.py
butler/countdown.py
butler/numbers.py
n8.butler-0.0.2.dist-info/LICENSE
n8.butler-0.0.2.dist-info/METADATA
n8.butler-0.0.2.dist-info/WHEEL
n8.butler-0.0.2.dist-info/top_level.txt
n8.butler-0.0.2.dist-info/RECORD
