Metadata-Version: 2.1
Name: n8.butler
Version: 0.0.2
Summary: It does a few things
Home-page: https://github.com/nidelva/butler
Author: Nidelva
Author-email: hi@n8.pm
License: MIT
Platform: UNKNOWN
Classifier: Programming Language :: Python :: 3
Classifier: License :: OSI Approved :: MIT License
Classifier: Operating System :: OS Independent
